project_func/.DS_Store
project_func/__init__.py
project_func/cli.py
project_func/scripts/.DS_Store
project_func/scripts/__init__.py
project_func/scripts/main_base.py
project_prohorenkov_b24_506-0.1.0.dist-info/METADATA
project_prohorenkov_b24_506-0.1.0.dist-info/WHEEL
project_prohorenkov_b24_506-0.1.0.dist-info/entry_points.txt
project_prohorenkov_b24_506-0.1.0.dist-info/RECORD
