Metadata-Version: 2.1
Name: project-prohorenkov-b24-506
Version: 0.1.0
Summary: 
Author: Daniil
Author-email: danprohorenkov@yandex.ru
Requires-Python: >=3.13,<4.0
Classifier: Programming Language :: Python :: 3
Classifier: Programming Language :: Python :: 3.13
Requires-Dist: prompt (>=0.4.1,<0.5.0)
